litestar_users/__init__.py
litestar_users/cli.py
litestar_users/config.py
litestar_users/dependencies.py
litestar_users/dtos.py
litestar_users/exceptions.py
litestar_users/guards.py
litestar_users/jwt.py
litestar_users/main.py
litestar_users/password.py
litestar_users/protocols.py
litestar_users/py.typed
litestar_users/route_handlers.py
litestar_users/schema.py
litestar_users/service.py
litestar_users/user_handlers.py
litestar_users/utils.py
litestar_users/adapter/__init__.py
litestar_users/adapter/sqlalchemy/__init__.py
litestar_users/adapter/sqlalchemy/mixins.py
litestar_users/adapter/sqlalchemy/protocols.py
litestar_users/adapter/sqlalchemy/repository.py
litestar_users-1.7.0.dist-info/METADATA
litestar_users-1.7.0.dist-info/WHEEL
litestar_users-1.7.0.dist-info/licenses/LICENSE
litestar_users-1.7.0.dist-info/RECORD
