Metadata-Version: 2.4
Name: litestar-users
Version: 1.7.0
Summary: Authentication and user management for Litestar
Author-email: Michael Bosch <michael@vonbosch.co.za>
License-Expression: MIT
License-File: LICENSE
Requires-Python: ~=3.9
Requires-Dist: advanced-alchemy>=0.31.0
Requires-Dist: argon2-cffi
Requires-Dist: cryptography
Requires-Dist: libpass<2,>=1.8.1
Requires-Dist: litestar[cli,jwt,sqlalchemy]<3,>=2.9.0
Requires-Dist: pyjwt>=2.10.1
Requires-Dist: pyyaml!=5.4.*
Provides-Extra: oauth2
Requires-Dist: httpx-oauth>=0.16.1; extra == 'oauth2'
